LICENSE.txt
MANIFEST.in
README.rst
setup.py
polyfinder/__init__.py
polyfinder.egg-info/PKG-INFO
polyfinder.egg-info/SOURCES.txt
polyfinder.egg-info/dependency_links.txt
polyfinder.egg-info/requires.txt
polyfinder.egg-info/top_level.txt
polyfinder/tests/__init__.py