Metadata-Version: 1.1
Name: polyfinder
Version: 0.1
Summary: UNKNOWN
Home-page: http://github.com/joetric/polyfinder
Author: Joseph R. Tricarico
Author-email: jtricarico@gmail.com
License: MIT
Platform: UNKNOWN
Classifier: Development Status :: 4 - Beta
Classifier: License :: OSI Approved :: MIT License
Classifier: Topic :: Scientific/Engineering :: GIS
Classifier: Programming Language :: Python :: 2.7
